dhpackagetest/__init__.py
dhpackagetest/dhmoduletest.py
dhpackagetest-0.1.dist-info/METADATA
dhpackagetest-0.1.dist-info/WHEEL
dhpackagetest-0.1.dist-info/top_level.txt
dhpackagetest-0.1.dist-info/RECORD
