Metadata-Version: 2.1
Name: dhpackagetest
Version: 0.1
Summary: The funniest joke in the world
Home-page: http://github.com/danahynes/dhconfiguratorv1
Author: Dana Hynes
Author-email: danhynes@example.com
License: WTFPLv2
Keywords: funniest joke comedy flying circus
